CAINNLinearRegression
