Metadata-Version: 1.0
Name: CAINNLinearRegression
Version: 1.0.4
Summary: Linear Regression modeling algorithm
Home-page: UNKNOWN
Author: Christopher Weaver
Author-email: crweaver225@yahoo.com
License: UNKNOWN
Platform: UNKNOWN
